create_pypi_files/__init__.py
create_pypi_files/create.py
create_pypi_files-0.0.3.dist-info/METADATA
create_pypi_files-0.0.3.dist-info/WHEEL
create_pypi_files-0.0.3.dist-info/license_files/LICENSE
create_pypi_files-0.0.3.dist-info/RECORD
